{
  "Deadline": "pink",
  "Fawkes Night": "green",
  "Pepe Plans": "silver",
  "Balloon Face": "pink",
  "Burning Time": "silver",
  "Independence": "silver",
  "Adult Tasks": "gray",
  "Investor": "gold",
  "Hodler": "silver",
  "Luftballons": "silver",
  "Peach Week": "silver",
  "Checklist": "silver",
  "Durov Day": "gold",
  "Celebration": "silver",
  "Sherlock": "silver",
  "Tic Tac Toe": "silver",
  "Fund Manager": "pink",
  "Telegram": "gray",
  "June": "silver",
  "Tuesday": "silver",
  "May": "silver",
  "Thursday": "silver",
  "September": "gold",
  "Saturday": "silver",
  "Heartbreak": "pink",
  "August": "gray",
  "July": "gold",
  "Wednesday": "silver",
  "January": "silver",
  "November": "silver",
  "Friday": "pink",
  "Sunday": "silver",
  "Monday": "silver",
  "October": "pink",
  "Festive Day": "silver",
  "March": "silver",
  "February": "pink",
  "Like Cycle": "pink",
  "December": "silver",
  "April": "silver",
  "Day Five": "silver",
  "Gato Ocho": "silver",
  "Ninety Nine": "gold",
  "Rare Event": "silver",
  "Kawaii": "gray",
  "Crossed Out": "gray",
  "Groundhog Day": "gold",
  "Blank Page": "pink",
  "Shocktober": "brown",
  "Fresh Start": "silver",
  "Blueprint": "silver",
  "Pink Planner": "purple",
  "Newsprint": "gold",
  "Golden Years": "gold",
  "Pink Hearts": "pink",
  "Monochrome": "silver",
  "Dark Binding": "gray",
  "Strong Circle": "silver",
  "Lavendays": "pink",
  "Orange Mood": "silver",
  "Tropical": "silver",
  "Highlighter": "gray",
  "Beet Diary": "silver",
  "Red Pen": "silver",
  "Eco Friendly": "silver",
  "Blue Sky": "silver",
  "Blossoms": "pink",
  "Leather Top": "silver",
  "Sticky Note": "pink",
  "Going Green": "silver",
  "Gold Pink": "pink",
  "Fire Path": "gold",
  "Purple Mint": "silver",
  "Bright Coral": "silver",
  "Very Visible": "gray",
  "Choco Top": "gray",
  "Harvest": "gold",
  "Lemon": "silver",
  "Black Flip": "gray",
  "Green Day": "silver",
  "Golden Touch": "gray",
  "Magic Flow": "pink",
  "Lovely": "pink",
  "Plum Peach": "pink",
  "Barbie Day": "silver",
  "Party Time": "silver",
  "Black Suede": "silver",
  "Basic Blue": "silver",
  "Yellow Page": "silver",
  "Lilac Black": "gray",
  "Pink Day": "pink",
  "Purple Front": "gray",
  "Surfer": "silver",
  "Deep Ocean": "gray",
  "Minting Date": "cyan",
  "Sunshine": "silver",
  "Gold Leaf": "gold",
  "Beachy": "silver",
  "Miami Beach": "silver",
  "The Nineties": "pink"
}