{
  "Diamond Hands": "silver",
  "In Bloom": "pink",
  "Smitten": "pink",
  "Polaris": "orange",
  "Fortune": "gold",
  "Wet Clap": "silver",
  "Astronaut": "purple",
  "Fire Nation": "brown",
  "Static Shock": "gray",
  "Jelly Bears": "green",
  "Water Bender": "silver",
  "Starburst": "silver",
  "Telegram": "silver",
  "Menthol": "green",
  "Milkmaid": "gray",
  "Hive Five": "orange",
  "Pink Sparkle": "pink",
  "Woodman": "silver",
  "Star Power": "pink",
  "Narcissus": "gold",
  "Blizzard": "gray",
  "Cheetah": "brown",
  "Arborist": "green",
  "Shortcake": "silver",
  "Stripe Knot": "pink",
  "Dinosaurs": "gray",
  "Holly Hands": "brown",
  "Frost Fingers": "silver",
  "LED Lights": "silver",
  "Tartan Flake": "gray",
  "Twinkle": "pink",
  "Pingu": "gray",
  "Two Hearts": "gray",
  "Red Polka": "gray",
  "November": "gray",
  "Golden Pine": "green",
  "Candy Cane": "brown",
  "Ruby Rhombus": "pink",
  "Rudolph": "gray",
  "Grandma": "gray",
  "Kitten-Mittens": "silver",
  "Red Skater": "pink",
  "Amanita": "brown",
  "Santa Claus": "brown",
  "Skellington": "gray",
  "Moulin Rouge": "brown",
  "Cute Bunnies": "pink",
  "Santa’s Gifts": "gray",
  "Fursona": "gold",
  "Ladybug": "brown",
  "Alpine Fern": "green",
  "Aubergine": "purple",
  "Bright Lilac": "silver",
  "Mistletoe": "silver",
  "Iceland": "silver",
  "Frosty Pink": "silver",
  "Currant": "brown",
  "Cherry": "purple",
  "Evergreen": "silver",
  "Pistachio": "silver",
  "Honey Wine": "pink",
  "Pyrite": "silver",
  "Carnation": "pink",
  "Salmon": "pink",
  "Orchid": "pink",
  "Amethyst": "purple",
  "Periwinkle": "silver",
  "Raspberry": "purple",
  "Grape Soda": "purple",
  "New Year": "pink",
  "Mocha": "gray",
  "Seafoam": "silver",
  "Lipstick": "pink",
  "Pink Cuffs": "gray",
  "Gold Thread": "pink",
  "Flamingo": "pink",
  "Champagne": "orange",
  "White Pear": "gold",
  "Brown Suede": "brown",
  "Greenland": "green",
  "Lapland": "gray",
  "Milk Tea": "pink",
  "Twilight": "purple",
  "Dark Grape": "purple",
  "Green Gloves": "cyan",
  "Anemone": "pink",
  "Bechamel": "silver",
  "Heather": "pink",
  "Cedar": "gold",
  "Karelia": "silver",
  "Father Frost": "brown",
  "Daydream": "pink",
  "Sencha": "cyan",
  "Mintens": "silver",
  "Burgundy": "gray",
  "The Riddler": "gray",
  "Norway": "silver",
  "Mauvelous": "pink",
  "Blueberry": "purple",
  "Sequoia": "gray"
}