{
  "Diamond Hands": "white",
  "In Bloom": "red",
  "Smitten": "white",
  "Polaris": "orange",
  "Fortune": "orange",
  "Wet Clap": "cyan",
  "Astronaut": "blue",
  "Fire Nation": "red",
  "Static Shock": "blue",
  "Jelly Bears": "green",
  "Water Bender": "cyan",
  "Starburst": "cyan",
  "Telegram": "cyan",
  "Menthol": "green",
  "Milkmaid": "white",
  "Hive Five": "orange",
  "Pink Sparkle": "purple",
  "Woodman": "green",
  "Star Power": "pink",
  "Narcissus": "cyan",
  "Blizzard": "blue",
  "Cheetah": "red",
  "Arborist": "yellow",
  "Shortcake": "red",
  "Stripe Knot": "red",
  "Dinosaurs": "cyan",
  "Holly Hands": "red",
  "Frost Fingers": "white",
  "LED Lights": "white",
  "Tartan Flake": "red",
  "Twinkle": "red",
  "Pingu": "white",
  "Two Hearts": "white",
  "Red Polka": "red",
  "November": "red",
  "Golden Pine": "cyan",
  "Candy Cane": "red",
  "Ruby Rhombus": "pink",
  "Rudolph": "red",
  "Grandma": "red",
  "Kitten-Mittens": "white",
  "Red Skater": "red",
  "Amanita": "gray",
  "Santa Claus": "red",
  "Skellington": "black",
  "Moulin Rouge": "red",
  "Cute Bunnies": "orange",
  "Santa’s Gifts": "green",
  "Fursona": "red",
  "Ladybug": "black",
  "Alpine Fern": "green",
  "Aubergine": "white",
  "Bright Lilac": "blue",
  "Mistletoe": "white",
  "Iceland": "white",
  "Frosty Pink": "cyan",
  "Currant": "red",
  "Cherry": "pink",
  "Evergreen": "green",
  "Pistachio": "yellow",
  "Honey Wine": "pink",
  "Pyrite": "orange",
  "Carnation": "white",
  "Salmon": "red",
  "Orchid": "pink",
  "Amethyst": "pink",
  "Periwinkle": "white",
  "Raspberry": "white",
  "Grape Soda": "pink",
  "New Year": "red",
  "Mocha": "red",
  "Seafoam": "white",
  "Lipstick": "pink",
  "Pink Cuffs": "blue",
  "Gold Thread": "red",
  "Flamingo": "white",
  "Champagne": "orange",
  "White Pear": "white",
  "Brown Suede": "red",
  "Greenland": "green",
  "Lapland": "cyan",
  "Milk Tea": "white",
  "Twilight": "blue",
  "Dark Grape": "purple",
  "Green Gloves": "cyan",
  "Anemone": "red",
  "Bechamel": "white",
  "Heather": "white",
  "Cedar": "red",
  "Karelia": "white",
  "Father Frost": "red",
  "Daydream": "blue",
  "Sencha": "cyan",
  "Mintens": "white",
  "Burgundy": "red",
  "The Riddler": "purple",
  "Norway": "blue",
  "Mauvelous": "blue",
  "Blueberry": "blue",
  "Sequoia": "cyan"
}